fulladder_struct.v
module fulladder_struct(
    input X1, X2, Cin,
    output S, Cout
);

wire w1, w2, w3;
xor u1(w1, X1, X2);
and u2(w2, X1, X2);
and u3(w3, w1, Cin);
or u4(Cout, w2, a3);
xor u5(S,w1,Cin);

endmodule

fulladder_struct_tb.v
`timescale 1ns / 1ns
module fulladder_tb();
    reg A,B,Cin;
    wire S,Cout;

    fulladder_struct uut(
        .X1(A),
        .X2(B),
        .Cin(Cin),
        .Cout(Cout),
        .S(S)
    );
    initial begin
        $dumpfile("fulladder_struct_tb.vcd");
        $dumpvars(0, fulladder_tb);

        A=0;
        B=0;
        Cin=0;
        #5;

        A=0;
        B=0;
        Cin=1;
        #5;

        A=0;
        B=1;
        Cin=0;
        #5;

        A=0;
        B=1;
        Cin=1;
        #5;

        A=1;
        B=0;
        Cin=0;
        #5;

        A=1;
        B=0;
        Cin=1;
        #5;

        A=1;
        B=1;
        Cin=0;
        #5;

        A=1;
        B=1;
        Cin=1;
        #5;
    end
endmodule

fulladder_struct_tb.vcd
$date
	Wed Sep  3 18:42:19 2025
$end
$version
	Icarus Verilog
$end
$timescale
	1ns
$end
$scope module fulladder_tb $end
$var wire 1 ! S $end
$var wire 1 " Cout $end
$var reg 1 # A $end
$var reg 1 $ B $end
$var reg 1 % Cin $end
$scope module uut $end
$var wire 1 % Cin $end
$var wire 1 " Cout $end
$var wire 1 ! S $end
$var wire 1 # X1 $end
$var wire 1 $ X2 $end
$var wire 1 & a3 $end
$var wire 1 ' w1 $end
$var wire 1 ( w2 $end
$var wire 1 ) w3 $end
$upscope $end
$upscope $end
$enddefinitions $end
$comment Show the parameter values. $end
$dumpall
$end
#0
$dumpvars
0)
0(
0'
z&
0%
0$
0#
x"
0!
$end
#5
1!
1%
#10
1'
0%
1$
#15
1)
0!
1%
#20
0)
1!
0%
0$
1#
#25
1)
0!
1%
#30
1"
0)
0'
1(
0%
1$
#35
1!
1%
