fulladder.v
module fulladder(
    input X1, X2, Cin,
    output S,Cout
    );

        reg [1:0] temp;
    always @(*)
    begin
        temp={1'b0,X1} + {1'b0,X2} + {1'b0,Cin};
    end
    assign S= temp[0];
    assign Cout = temp [1];

endmodule

fulladder_tb.v
`timescale 10ns / 10ps
module fulladder_tb();
    reg A,B,Cin;
    wire S,Cout;

    fulladder uut(
        .X1(A),
        .X2(B),
        .Cin(Cin),
        .Cout(Cout),
        .S(S)
    );
    initial begin
        $dumpfile("fulladder_tb.vcd");
        $dumpvars(0, fulladder_tb);

        A=0;
        B=0;
        Cin=0;
        #5;

        A=0;
        B=0;
        Cin=1;
        #5;

        A=0;
        B=1;
        Cin=0;
        #5;

        A=0;
        B=1;
        Cin=1;
        #5;

        A=1;
        B=0;
        Cin=0;
        #5;

        A=1;
        B=0;
        Cin=1;
        #5;

        A=1;
        B=1;
        Cin=0;
        #5;

        A=1;
        B=1;
        Cin=1;
        #5;
    end
endmodule

fulladder_tb.vcd
$date
	Wed Sep  3 17:56:58 2025
$end
$version
	Icarus Verilog
$end
$timescale
	10ps
$end
$scope module fulladder_tb $end
$var wire 1 ! S $end
$var wire 1 " Cout $end
$var reg 1 # A $end
$var reg 1 $ B $end
$var reg 1 % Cin $end
$scope module uut $end
$var wire 1 % Cin $end
$var wire 1 # X1 $end
$var wire 1 $ X2 $end
$var wire 1 ! S $end
$var wire 1 " Cout $end
$var reg 2 & temp [1:0] $end
$upscope $end
$upscope $end
$enddefinitions $end
$comment Show the parameter values. $end
$dumpall
$end
#0
$dumpvars
b0 &
0%
0$
0#
0"
0!
$end
#5000
1!
b1 &
1%
#10000
0%
1$
#15000
0!
1"
b10 &
1%
#20000
1!
0"
b1 &
0%
0$
1#
#25000
0!
1"
b10 &
1%
#30000
0%
1$
#35000
1!
b11 &
1%
